{
  "project_info": {
    "project_number": "846715888080",
    "project_id": "watercare-co227",
    "storage_bucket": "watercare-co227.appspot.com"
  },
  "client": [
    {
      "client_info": {
        "mobilesdk_app_id": "1:846715888080:android:0d1221545bbf2431d699d5",
        "android_client_info": {
          "package_name": "com.example.co227"
        }
      },
      "oauth_client": [
        {
          "client_id": "846715888080-k4pnd42cuem121m0jkjp4ft5evovmn1c.apps.googleusercontent.com",
          "client_type": 3
        }
      ],
      "api_key": [
        {
          "current_key": "AIzaSyBjguoP_TbTJv30jh8BSidXUPI9hU2GPgY"
        }
      ],
      "services": {
        "appinvite_service": {
          "other_platform_oauth_client": [
            {
              "client_id": "846715888080-k4pnd42cuem121m0jkjp4ft5evovmn1c.apps.googleusercontent.com",
              "client_type": 3
            }
          ]
        }
      }
    }
  ],
  "configuration_version": "1"
}